{
  "year": 2026,
  "source": "kalshi",
  "fetched_at": "2026-04-28T16:15:40+00:00",
  "n_sims": 1000,
  "slots": [
    {
      "round": "FINALS",
      "conference": null,
      "slot": "FINALS",
      "candidates": [
        {
          "team": "OKC",
          "seed": null,
          "wins": [
            0,
            0,
            0,
            484
          ]
        },
        {
          "team": "SAS",
          "seed": null,
          "wins": [
            0,
            0,
            0,
            152
          ]
        },
        {
          "team": "BOS",
          "seed": null,
          "wins": [
            0,
            0,
            0,
            143
          ]
        },
        {
          "team": "DEN",
          "seed": null,
          "wins": [
            0,
            0,
            0,
            41
          ]
        },
        {
          "team": "CLE",
          "seed": null,
          "wins": [
            0,
            0,
            0,
            41
          ]
        },
        {
          "team": "LAL",
          "seed": null,
          "wins": [
            0,
            0,
            0,
            32
          ]
        },
        {
          "team": "NYK",
          "seed": null,
          "wins": [
            0,
            0,
            0,
            23
          ]
        },
        {
          "team": "DET",
          "seed": null,
          "wins": [
            0,
            0,
            0,
            18
          ]
        },
        {
          "team": "MIN",
          "seed": null,
          "wins": [
            0,
            0,
            0,
            9
          ]
        },
        {
          "team": "HOU",
          "seed": null,
          "wins": [
            0,
            0,
            0,
            9
          ]
        },
        {
          "team": "ORL",
          "seed": null,
          "wins": [
            0,
            0,
            0,
            9
          ]
        },
        {
          "team": "TOR",
          "seed": null,
          "wins": [
            0,
            0,
            0,
            9
          ]
        },
        {
          "team": "POR",
          "seed": null,
          "wins": [
            0,
            0,
            0,
            9
          ]
        },
        {
          "team": "ATL",
          "seed": null,
          "wins": [
            0,
            0,
            0,
            9
          ]
        },
        {
          "team": "PHI",
          "seed": null,
          "wins": [
            0,
            0,
            0,
            9
          ]
        }
      ],
      "series": null
    },
    {
      "round": "CONF_FINALS",
      "conference": "East",
      "slot": "E_CF",
      "candidates": [
        {
          "team": "BOS",
          "seed": null,
          "wins": [
            0,
            0,
            0,
            512
          ]
        },
        {
          "team": "CLE",
          "seed": null,
          "wins": [
            0,
            0,
            0,
            210
          ]
        },
        {
          "team": "NYK",
          "seed": null,
          "wins": [
            0,
            0,
            0,
            132
          ]
        },
        {
          "team": "DET",
          "seed": null,
          "wins": [
            0,
            0,
            0,
            54
          ]
        },
        {
          "team": "ORL",
          "seed": null,
          "wins": [
            0,
            0,
            0,
            44
          ]
        },
        {
          "team": "ATL",
          "seed": null,
          "wins": [
            0,
            0,
            0,
            24
          ]
        },
        {
          "team": "TOR",
          "seed": null,
          "wins": [
            0,
            0,
            0,
            15
          ]
        },
        {
          "team": "PHI",
          "seed": null,
          "wins": [
            0,
            0,
            0,
            10
          ]
        }
      ],
      "series": null
    },
    {
      "round": "CONF_FINALS",
      "conference": "West",
      "slot": "W_CF",
      "candidates": [
        {
          "team": "OKC",
          "seed": null,
          "wins": [
            0,
            0,
            0,
            621
          ]
        },
        {
          "team": "SAS",
          "seed": null,
          "wins": [
            0,
            0,
            0,
            232
          ]
        },
        {
          "team": "LAL",
          "seed": null,
          "wins": [
            0,
            0,
            0,
            62
          ]
        },
        {
          "team": "DEN",
          "seed": null,
          "wins": [
            0,
            0,
            0,
            52
          ]
        },
        {
          "team": "MIN",
          "seed": null,
          "wins": [
            0,
            0,
            0,
            14
          ]
        },
        {
          "team": "HOU",
          "seed": null,
          "wins": [
            0,
            0,
            0,
            9
          ]
        },
        {
          "team": "POR",
          "seed": null,
          "wins": [
            0,
            0,
            0,
            9
          ]
        }
      ],
      "series": null
    },
    {
      "round": "R1",
      "conference": "West",
      "slot": "W_2_7",
      "candidates": [
        {
          "team": "SAS",
          "seed": 2,
          "wins": [
            0,
            820,
            117,
            44
          ]
        },
        {
          "team": "POR",
          "seed": 7,
          "wins": [
            0,
            0,
            0,
            20
          ]
        }
      ],
      "series": null
    },
    {
      "round": "R1",
      "conference": "East",
      "slot": "E_2_7",
      "candidates": [
        {
          "team": "BOS",
          "seed": 2,
          "wins": [
            0,
            797,
            130,
            53
          ]
        },
        {
          "team": "PHI",
          "seed": 7,
          "wins": [
            0,
            0,
            0,
            19
          ]
        }
      ],
      "series": null
    },
    {
      "round": "R1",
      "conference": "East",
      "slot": "E_4_5",
      "candidates": [
        {
          "team": "CLE",
          "seed": 4,
          "wins": [
            0,
            0,
            437,
            357
          ]
        },
        {
          "team": "TOR",
          "seed": 5,
          "wins": [
            0,
            0,
            101,
            106
          ]
        }
      ],
      "series": null
    },
    {
      "round": "R1",
      "conference": "East",
      "slot": "E_1_8",
      "candidates": [
        {
          "team": "ORL",
          "seed": 8,
          "wins": [
            0,
            242,
            348,
            106
          ]
        },
        {
          "team": "DET",
          "seed": 1,
          "wins": [
            0,
            0,
            0,
            303
          ]
        }
      ],
      "series": null
    },
    {
      "round": "R1",
      "conference": "West",
      "slot": "W_3_6",
      "candidates": [
        {
          "team": "DEN",
          "seed": 3,
          "wins": [
            0,
            0,
            0,
            555
          ]
        },
        {
          "team": "MIN",
          "seed": 6,
          "wins": [
            0,
            0,
            303,
            142
          ]
        }
      ],
      "series": null
    },
    {
      "round": "R1",
      "conference": "West",
      "slot": "W_4_5",
      "candidates": [
        {
          "team": "LAL",
          "seed": 4,
          "wins": [
            0,
            593,
            167,
            118
          ]
        },
        {
          "team": "HOU",
          "seed": 5,
          "wins": [
            0,
            0,
            0,
            123
          ]
        }
      ],
      "series": null
    },
    {
      "round": "R1",
      "conference": "East",
      "slot": "E_3_6",
      "candidates": [
        {
          "team": "NYK",
          "seed": 3,
          "wins": [
            0,
            0,
            355,
            340
          ]
        },
        {
          "team": "ATL",
          "seed": 6,
          "wins": [
            0,
            0,
            153,
            153
          ]
        }
      ],
      "series": null
    }
  ]
}
